lorcania_cli/__init__.py
lorcania_cli/__main__.py
lorcania_cli/api/__init__.py
lorcania_cli/api/lorcania.py
lorcania_cli/collection.py
lorcania_cli/main.py
lorcania_cli-0.1.1.dist-info/entry_points.txt
lorcania_cli-0.1.1.dist-info/LICENSE
lorcania_cli-0.1.1.dist-info/METADATA
lorcania_cli-0.1.1.dist-info/WHEEL
lorcania_cli-0.1.1.dist-info/RECORD
